my_investment/__init__.py
my_investment/core.py
my_investment_package-1.0.0.dist-info/METADATA
my_investment_package-1.0.0.dist-info/WHEEL
my_investment_package-1.0.0.dist-info/top_level.txt
my_investment_package-1.0.0.dist-info/RECORD
