Metadata-Version: 2.4
Name: my_investment-package
Version: 1.0.0
Summary: Descricao da sua lib my_investment
Home-page: https://github.com/tadrianonet/my_investment
Author: Matheus
Author-email: matheus@example.com
License: MIT
Dynamic: author
Dynamic: author-email
Dynamic: description
Dynamic: description-content-type
Dynamic: home-page
Dynamic: license
Dynamic: summary
